<?xml version="1.0" encoding="utf-8"?>
<AssetDocuments xmlns:xsi="http://www.w3.org/2001/XMLSchema-instance" xmlns:xsd="http://www.w3.org/2001/XMLSchema">
  <AssetDocument>
    <AssetId>1</AssetId>
    <DocumentId>1</DocumentId>
    <Date>2023-01-15T00:00:00+02:00</Date>
  </AssetDocument>
  <AssetDocument>
    <AssetId>3</AssetId>
    <DocumentId>2</DocumentId>
    <Date>2023-04-05T00:00:00</Date>
  </AssetDocument>
  <AssetDocument>
    <AssetId>4</AssetId>
    <DocumentId>3</DocumentId>
    <Date>2023-07-30T00:00:00</Date>
  </AssetDocument>
  <AssetDocument>
    <AssetId>5</AssetId>
    <DocumentId>7</DocumentId>
    <Date>2023-08-08T00:00:00</Date>
  </AssetDocument>
  <AssetDocument>
    <AssetId>6</AssetId>
    <DocumentId>3</DocumentId>
    <Date>2023-09-16T00:00:00</Date>
  </AssetDocument>
  <AssetDocument>
    <AssetId>7</AssetId>
    <DocumentId>1</DocumentId>
    <Date>2023-08-08T00:00:00</Date>
  </AssetDocument>
  <AssetDocument>
    <AssetId>8</AssetId>
    <DocumentId>6</DocumentId>
    <Date>2023-11-15T00:00:00</Date>
  </AssetDocument>
  <AssetDocument>
    <AssetId>9</AssetId>
    <DocumentId>5</DocumentId>
    <Date>2023-12-28T00:00:00</Date>
  </AssetDocument>
  <AssetDocument>
    <AssetId>10</AssetId>
    <DocumentId>7</DocumentId>
    <Date>2024-01-10T00:00:00</Date>
  </AssetDocument>
  <AssetDocument>
    <AssetId>1</AssetId>
    <DocumentId>4</DocumentId>
    <Date>2024-02-05T00:00:00</Date>
  </AssetDocument>
  <AssetDocument>
    <AssetId>2</AssetId>
    <DocumentId>8</DocumentId>
    <Date>2024-03-20T00:00:00</Date>
  </AssetDocument>
  <AssetDocument>
    <AssetId>3</AssetId>
    <DocumentId>5</DocumentId>
    <Date>2024-04-12T00:00:00</Date>
  </AssetDocument>
  <AssetDocument>
    <AssetId>4</AssetId>
    <DocumentId>4</DocumentId>
    <Date>2024-05-30T00:00:00</Date>
  </AssetDocument>
  <AssetDocument>
    <AssetId>5</AssetId>
    <DocumentId>6</DocumentId>
    <Date>2024-06-08T00:00:00</Date>
  </AssetDocument>
  <AssetDocument>
    <AssetId>6</AssetId>
    <DocumentId>9</DocumentId>
    <Date>2024-07-16T00:00:00</Date>
  </AssetDocument>
  <AssetDocument>
    <AssetId>11</AssetId>
    <DocumentId>6</DocumentId>
    <Date>2023-11-15T00:00:00</Date>
  </AssetDocument>
  <AssetDocument>
    <AssetId>12</AssetId>
    <DocumentId>5</DocumentId>
    <Date>2023-12-28T00:00:00</Date>
  </AssetDocument>
  <AssetDocument>
    <AssetId>13</AssetId>
    <DocumentId>7</DocumentId>
    <Date>2024-01-10T00:00:00</Date>
  </AssetDocument>
  <AssetDocument>
    <AssetId>14</AssetId>
    <DocumentId>4</DocumentId>
    <Date>2024-02-05T00:00:00</Date>
  </AssetDocument>
  <AssetDocument>
    <AssetId>15</AssetId>
    <DocumentId>8</DocumentId>
    <Date>2024-03-20T00:00:00</Date>
  </AssetDocument>
  <AssetDocument>
    <AssetId>16</AssetId>
    <DocumentId>5</DocumentId>
    <Date>2024-04-12T00:00:00</Date>
  </AssetDocument>
  <AssetDocument>
    <AssetId>17</AssetId>
    <DocumentId>4</DocumentId>
    <Date>2024-05-30T00:00:00</Date>
  </AssetDocument>
  <AssetDocument>
    <AssetId>18</AssetId>
    <DocumentId>6</DocumentId>
    <Date>2024-06-08T00:00:00</Date>
  </AssetDocument>
  <AssetDocument>
    <AssetId>18</AssetId>
    <DocumentId>9</DocumentId>
    <Date>2024-07-16T00:00:00</Date>
  </AssetDocument>
</AssetDocuments>